pubtatortool/__init__.py
pubtatortool/pubtator_corpus.py
pubtatortool/pubtator_document.py
pubtatortool/tokenization.py
pubtatortool-0.2.dist-info/METADATA
pubtatortool-0.2.dist-info/WHEEL
pubtatortool-0.2.dist-info/top_level.txt
pubtatortool-0.2.dist-info/RECORD
