Metadata-Version: 2.1
Name: pubtatortool
Version: 0.2
Summary: A package for loading and manipulating PubTator files as Python objects.
Home-page: https://github.com/gpiat/PubTator-Parsing-Tool
Author: Guilhem Piat
Author-email: guilhem.piat@protonmail.com
License: UNKNOWN
Platform: UNKNOWN
Classifier: Programming Language :: Python :: 3
Classifier: License :: Public Domain
Classifier: Operating System :: OS Independent
Requires-Python: >=3.6
